{
 "SoundBanksInfo": {
  "Platform": "Windows",
  "BasePlatform": "Windows",
  "SchemaVersion": "12",
  "SoundbankVersion": "135",
  "RootPaths": {
   "ProjectRoot": "E:\\Wwise\\Test\\",
   "SourceFilesRoot": "E:\\Wwise\\Test\\.cache\\Windows\\",
   "SoundBanksRoot": "E:\\Wwise\\Test\\GeneratedSoundBanks\\Windows\\",
   "ExternalSourcesInputFile": "",
   "ExternalSourcesOutputRoot": "E:\\Wwise\\Test\\GeneratedSoundBanks\\Windows"
  },
  "DialogueEvents": [],
  "StreamedFiles": [],
  "MediaFilesNotInAnyBank": [],
  "SoundBanks": [
   {
    "Id": "1355168291",
    "Language": "SFX",
    "Hash": "4204904655",
    "ObjectPath": "Init",
    "ShortName": "Init",
    "Path": "Init.bnk"
   },
   {
    "Id": "3157003241",
    "Language": "SFX",
    "Hash": "2148186179",
    "ObjectPath": "\\SoundBanks\\Default Work Unit\\Test",
    "ShortName": "Test",
    "Path": "Test.bnk",
    "IncludedEvents": [
     {
      "Id": "1256202815",
      "Name": "Play",
      "ObjectPath": "\\Events\\Default Work Unit\\Play",
      "IncludedMemoryFiles": [
       {
        "Id": "589915161",
        "Language": "SFX",
        "ShortName": "LegendsNeverDie.wav",
        "Path": "SFX\\LegendsNeverDie_10C4C929.wem"
       }
      ]
     }
    ]
   }
  ]
 }
}